NotesMaker/__init__.py
notesmaker-1.0.0.dist-info/METADATA
notesmaker-1.0.0.dist-info/WHEEL
notesmaker-1.0.0.dist-info/top_level.txt
notesmaker-1.0.0.dist-info/RECORD
