Metadata-Version: 2.4
Name: NotesMaker
Version: 1.0.0
Summary: This is an updated version of NotesMaker.py
Requires-Python: >=3.6
Dynamic: requires-python
Dynamic: summary
